odoo8_addon_mail_tracking-8.0.4.0.0-py2.7-nspkg.pth
odoo_addons/mail_tracking/__openerp__.py
odoo_addons/mail_tracking/hooks.py
odoo_addons/mail_tracking/__init__.py
odoo_addons/mail_tracking/README.rst
odoo_addons/mail_tracking/security/ir.model.access.csv
odoo_addons/mail_tracking/migrations/8.0.4.0.0/pre-migrate.py
odoo_addons/mail_tracking/models/res_partner.py
odoo_addons/mail_tracking/models/mail_message.py
odoo_addons/mail_tracking/models/mail_tracking_email.py
odoo_addons/mail_tracking/models/mail_mail.py
odoo_addons/mail_tracking/models/__init__.py
odoo_addons/mail_tracking/models/mail_tracking_event.py
odoo_addons/mail_tracking/models/ir_mail_server.py
odoo_addons/mail_tracking/i18n/pt.po
odoo_addons/mail_tracking/i18n/it.po
odoo_addons/mail_tracking/i18n/es.po
odoo_addons/mail_tracking/i18n/tr.po
odoo_addons/mail_tracking/i18n/gl.po
odoo_addons/mail_tracking/i18n/ca.po
odoo_addons/mail_tracking/i18n/sl.po
odoo_addons/mail_tracking/i18n/es_ES.po
odoo_addons/mail_tracking/i18n/pt_PT.po
odoo_addons/mail_tracking/i18n/nl.po
odoo_addons/mail_tracking/i18n/am.po
odoo_addons/mail_tracking/i18n/de.po
odoo_addons/mail_tracking/i18n/fr.po
odoo_addons/mail_tracking/i18n/pt_BR.po
odoo_addons/mail_tracking/i18n/el_GR.po
odoo_addons/mail_tracking/i18n/fi.po
odoo_addons/mail_tracking/views/res_partner_view.xml
odoo_addons/mail_tracking/views/assets.xml
odoo_addons/mail_tracking/views/mail_tracking_email_view.xml
odoo_addons/mail_tracking/views/mail_tracking_event_view.xml
odoo_addons/mail_tracking/controllers/main.py
odoo_addons/mail_tracking/controllers/__init__.py
odoo_addons/mail_tracking/data/tracking_data.xml
odoo_addons/mail_tracking/tests/test_mail_tracking.py
odoo_addons/mail_tracking/tests/__init__.py
odoo_addons/mail_tracking/static/description/icon.png
odoo_addons/mail_tracking/static/src/img/waiting.png
odoo_addons/mail_tracking/static/src/img/unknown.png
odoo_addons/mail_tracking/static/src/img/delivered.png
odoo8_addon_mail_tracking-8.0.4.0.0.dist-info/top_level.txt
odoo8_addon_mail_tracking-8.0.4.0.0.dist-info/WHEEL
odoo8_addon_mail_tracking-8.0.4.0.0.dist-info/RECORD
odoo8_addon_mail_tracking-8.0.4.0.0.dist-info/metadata.json
odoo8_addon_mail_tracking-8.0.4.0.0.dist-info/DESCRIPTION.rst
odoo8_addon_mail_tracking-8.0.4.0.0.dist-info/METADATA
odoo8_addon_mail_tracking-8.0.4.0.0.dist-info/namespace_packages.txt
